AUTHORS
CHANGELOG.txt
DESCRIPTION
LICENSE
MANIFEST.in
README.rst
setup.py
django_document_library.egg-info/PKG-INFO
django_document_library.egg-info/SOURCES.txt
django_document_library.egg-info/dependency_links.txt
django_document_library.egg-info/requires.txt
django_document_library.egg-info/top_level.txt
document_library/__init__.py
document_library/admin.py
document_library/cms_app.py
document_library/cms_plugins.py
document_library/models.py
document_library/settings.py
document_library/sitemaps.py
document_library/urls.py
document_library/views.py
document_library/migrations/0001_initial.py
document_library/migrations/0002_documentplugin.py
document_library/migrations/__init__.py
document_library/south_migrations/0001_initial.py
document_library/south_migrations/0002_auto__add_field_document_is_on_front_page.py
document_library/south_migrations/0003_auto__add_documentcategorytitle__add_documentcategory__add_field_docum.py
document_library/south_migrations/0004_auto__add_field_documentcategory_slug.py
document_library/south_migrations/0005_init_slug.py
document_library/south_migrations/0006_auto__chg_field_documentcategory_slug.py
document_library/south_migrations/0007_auto__add_field_document_source_url__add_field_document_download_url__.py
document_library/south_migrations/0008_auto.py
document_library/south_migrations/0009_auto.py
document_library/south_migrations/0010_auto__add_field_document_update_date.py
document_library/south_migrations/0011_auto__add_attachment.py
document_library/south_migrations/0012_auto__add_field_documenttitle_is_published.py
document_library/south_migrations/0013_transfer_is_published_from_document_to_title.py
document_library/south_migrations/0014_auto__del_field_document_is_published.py
document_library/south_migrations/0015_auto__add_documentplugin.py
document_library/south_migrations/0016_auto__add_field_documenttitle_meta_description.py
document_library/south_migrations/0017_auto__add_field_documenttitle_thumbnail.py
document_library/south_migrations/0018_auto__add_field_documentcategory_is_published__add_field_document_docu.py
document_library/south_migrations/0019_set_persistent_categories_to_published.py
