Metadata-Version: 1.0
Name: django-document-library
Version: 1.6.0
Summary: Django app to manage multilingual documents based on django-filer.
